Workbook

Sheet Overview
B2: TOEFL® Reading — Practice Question Bank
B3: 159 questions across the three passage types of the TOEFL iBT Reading section.
B5: Section | C5: Sets | D5: Questions | E5: What it tests
B6: Complete the Words | C6: =SUMPRODUCT(1/COUNTIF('Complete the Words'!B2:B101,'Complete the Words'!B2:B101)) | D6: =COUNT('Complete the Words'!A2:A101) | E6: Ten short paragraphs with letters removed; type the missing letters.
B7: Read in Daily Life | C7: =SUMPRODUCT(1/COUNTIF('Read in Daily Life'!B2:B35,'Read in Daily Life'!B2:B35)) | D7: =COUNT('Read in Daily Life'!A2:A35) | E7: Emails, announcements, and text chains. Purpose, detail, and inference.
B8: Read an Academic Passage | C8: =SUMPRODUCT(1/COUNTIF('Read an Academic Passage'!B2:B26,'Read an Academic Passage'!B2:B26)) | D8: =COUNT('Read an Academic Passage'!A2:A26) | E8: Three-paragraph passages: vocabulary, purpose, insert text, sentence select.
B9: Total | C9: =SUM(C6:C8) | D9: =SUM(D6:D8)
B12: Full tests
B13: Each pairs one passage of every type under a single clock — the shape of the real section.
B15: Test | C15: Minutes | D15: Questions | E15: Passages
B16: Full test 1 | C16: 18 | D16: 17 | E16: Rainforests · Textbook collection · The Evolution of Money
B17: Full test 2 | C17: 18 | D17: 18 | E17: How sound travels · Open-house volunteers · The Hidden Life of Soil
B18: Full test 3 | C18: 18 | D18: 18 | E18: Privacy online · Academic mentorship · Facial Recognition
B19: Full test 4 | C19: 18 | D19: 18 | E19: The sense of smell · Water service · The Pull of Nostalgia
B20: Full test 5 | C20: 18 | D20: 18 | E20: How we decide · Oakridge pool · The Rise of the Telegraph
B23: Source: 100 Practice Questions for the TOEFL® Reading Section (TST Prep, 2026 edition). Question numbers match that book. TOEFL® is a registered trademark of Educational Testing Service (ETS); this material is not endorsed or approved by ETS.

Sheet Complete the Words
A1: # | B1: Set | C1: Paragraph | D1: Stem shown | E1: Missing letters | F1: Complete word
A2: 1 | B2: 1 | C2: Rainforests | D2: Wa | E2: rm | F2: =D2&E2
A3: 2 | B3: 1 | C3: Rainforests | D3: a | E3: nd | F3: =D3&E3
A4: 3 | B4: 1 | C4: Rainforests | D4: ra | E4: in | F4: =D4&E4
A5: 4 | B5: 1 | C5: Rainforests | D5: t | E5: he | F5: =D5&E5
A6: 5 | B6: 1 | C6: Rainforests | D6: envi | E6: ronment | F6: =D6&E6
A7: 6 | B7: 1 | C7: Rainforests | D7: pl | E7: ants | F7: =D7&E7
A8: 7 | B8: 1 | C8: Rainforests | D8: gr | E8: ow | F8: =D8&E8
A9: 8 | B9: 1 | C9: Rainforests | D9: ye | E9: ar | F9: =D9&E9
A10: 9 | B10: 1 | C10: Rainforests | D10: le | E10: aves | F10: =D10&E10
A11: 10 | B11: 1 | C11: Rainforests | D11: a | E11: nd | F11: =D11&E11
A12: 11 | B12: 2 | C12: The Moon's surface | D12: bil | E12: lions | F12: =D12&E12
A13: 12 | B13: 2 | C13: The Moon's surface | D13: ye | E13: ars | F13: =D13&E13
... A101: 100 | B101: 10 | C101: How we decide | D101: al | E101: so | F101: =D101&E101

Sheet Cloze Paragraphs
A1: Set | B1: Title | C1: Blanks | D1: Paragraph as shown | E1: Paragraph solved
A2: 1 | B2: Rainforests | C2: 1–10 | D2: Rainforests are dense regions filled with tall trees and countless living things. Wa__ air a__ heavy ra__ create t__ ideal envi_______ for pl____ to gr__ all ye__. As le____ fall a__ decay, they return nutrients to the soil, supporting new life. Animals from insects to large cats depend on this balance for food and shelter. When large areas are cleared, the entire system weakens, and the forest struggles to recover. | E2: Rainforests are dense regions filled with tall trees and countless living things. Warm air and heavy rain create the ideal environment for plants to grow all year. As leaves fall and decay, they return nutrients to the soil, supporting new life. Animals from insects to large cats depend on this balance for food and shelter. When large areas are cleared, the entire system weakens, and the forest struggles to recover.
A3: 2 | B3: The Moon's surface | C3: 11–20 | D3: The Moon appears bright because its surface reflects sunlight toward Earth. Over bil_____ of ye___, countless imp____ have cov____ it wi__ fine du__ and ro__ fragments. Th___ scars re____ unchanged bec____ the Moon has no wind or rain to wear them away. Scientists study the patterns of craters to learn how often objects hit our solar system. Each mark on its surface tells a small part of the Moon's long and silent history. | E3: The Moon appears bright because its surface reflects sunlight toward Earth. Over billions of years, countless impacts have covered it with fine dust and rock fragments. These scars remain unchanged because the Moon has no wind or rain to wear them away. Scientists study the patterns of craters to learn how often objects hit our solar system. Each mark on its surface tells a small part of the Moon's long and silent history.
A4: 3 | B4: How sound travels | C4: 21–30 | D4: Sound travels as waves that move through air, water, or solid material. Wh__ something vib_____, it pu____ and pu___ nearby part_____, creating pat_____ of mot___ that o__ ears c__ detect. Fa____ vibrations make higher sounds, while slower ones produce deeper tones. The strength of these waves affects how loud the sound feels. Although invisible, sound connects people every day through voices, music, and the natural noises around us. | E4: Sound travels as waves that move through air, water, or solid material. When something vibrates, it pushes and pulls nearby particles, creating patterns of motion that our ears can detect. Faster vibrations make higher sounds, while slower ones produce deeper tones. The strength of these waves affects how loud the sound feels. Although invisible, sound connects people every day through voices, music, and the natural noises around us.
A5: 4 | B5: Working in a team | C5: 31–40 | D5: Working in a team allows people to combine different skills and ideas. Wh__ members li____ and sh___ openly, pro_____ can be so____ more crea______. Trust bu____ as pe____ depend o_ one ano____ to complete tasks, and motivation often increases when goals are shared. Disagreements will happen, but respectful communication keeps progress steady and prevents small issues from growing. A strong team doesn't mean everyone thinks alike—it means they move forward together despite their differences. | E5: Working in a team allows people to combine different skills and ideas. When members listen and share openly, problems can be solved more creatively. Trust builds as people depend on one another to complete tasks, and motivation often increases when goals are shared. Disagreements will happen, but respectful communication keeps progress steady and prevents small issues from growing. A strong team doesn't mean everyone thinks alike—it means they move forward together despite their differences.
A6: 5 | B6: Rivers | C6: 41–50 | D6: Rivers are always moving, shaping the land as they flow toward the sea. Ov__ time, wa___ wears aw__ rocks a__ soil, car____ valleys a__ creating n__ paths. Wh__ floods oc___, they c__ both damage land and deposit fresh layers of fertile earth. Towns often form along rivers because they offer water, travel routes, and trade. A river's constant motion reminds us that change in nature never truly stops. | E6: Rivers are always moving, shaping the land as they flow toward the sea. Over time, water wears away rocks and soil, carving valleys and creating new paths. When floods occur, they can both damage land and deposit fresh layers of fertile earth. Towns often form along rivers because they offer water, travel routes, and trade. A river's constant motion reminds us that change in nature never truly stops.
A7: 6 | B7: Privacy online | C7: 51–60 | D7: The rise of the internet has made sharing information easier than ever before. Ea__ time w_ browse, po__, or sh__ online, o__ data le____ a dig____ trace. Comp_____ use th__ information to imp____ services or advertise products, but it also raises concerns about privacy. Learning how to manage passwords, settings, and permissions helps people protect their personal information. In a connected world, privacy depends as much on awareness as on technology. | E7: The rise of the internet has made sharing information easier than ever before. Each time we browse, post, or shop online, our data leaves a digital trace. Companies use this information to improve services or advertise products, but it also raises concerns about privacy. Learning how to manage passwords, settings, and permissions helps people protect their personal information. In a connected world, privacy depends as much on awareness as on technology.
A8: 7 | B8: Living in a new culture | C8: 61–70 | D8: Moving to a new country often forces people to rethink how they express themselves. Beha_____ that fe__ natural i_ one cul____, such a_ how cl___ to st___ or wh__ to sp___, can se__ unusual in another. At first, these differences may cause confusion or even embarrassment, but over time they teach flexibility. People who learn to notice subtle social cues often discover that understanding others more clearly also changes how they see themselves. | E8: Moving to a new country often forces people to rethink how they express themselves. Behaviors that feel natural in one culture, such as how close to stand or when to speak, can seem unusual in another. At first, these differences may cause confusion or even embarrassment, but over time they teach flexibility. People who learn to notice subtle social cues often discover that understanding others more clearly also changes how they see themselves.
A9: 8 | B9: From hunting to farming | C9: 71–80 | D9: The shift from hunting to farming transformed early human life. Pe____ began pla_____ seeds a__ raising ani____ instead o_ moving cons______ in se____ of fo__. With rel_____ harvests, vil_____ grew, and families could settle in one place. This stability encouraged cooperation and the exchange of ideas among neighbors. Over time, farming not only provided food but also created the foundations for organized society and cultural progress. | E9: The shift from hunting to farming transformed early human life. People began planting seeds and raising animals instead of moving constantly in search of food. With reliable harvests, villages grew, and families could settle in one place. This stability encouraged cooperation and the exchange of ideas among neighbors. Over time, farming not only provided food but also created the foundations for organized society and cultural progress.
A10: 9 | B10: The sense of smell | C10: 81–90 | D10: Our sense of smell allows us to detect thousands of different scents. Wh__ we bre____ in, ti__ molecules tr____ through t__ nose a__ reach spe____ cells th__ send sig____ to the br___. Smell can trigger memories, emotions, and even hunger in an instant. Because of this close link to memory, a familiar scent can make someone recall a person or place from years ago. Scientists continue to study smell to understand how it influences behavior and emotional well-being in everyday life. | E10: Our sense of smell allows us to detect thousands of different scents. When we breathe in, tiny molecules travel through the nose and reach special cells that send signals to the brain. Smell can trigger memories, emotions, and even hunger in an instant. Because of this close link to memory, a familiar scent can make someone recall a person or place from years ago. Scientists continue to study smell to understand how it influences behavior and emotional well-being in everyday life.
A11: 10 | B11: How we decide | C11: 91–100 | D11: People make countless decisions every day, from simple choices to major life plans. Of___, the mi__ uses shor_____ to de____ quickly wit____ analyzing ev___ detail. Th___ shortcuts sa__ time b__ can al__ lead to mistakes when emotions take over. Slowing down and considering different viewpoints helps create more balanced decisions. Over time, experience teaches people when to trust their instincts and when to pause for deeper thought. Good judgment is not about speed—it's about matching action to the situation. | E11: People make countless decisions every day, from simple choices to major life plans. Often, the mind uses shortcuts to decide quickly without analyzing every detail. These shortcuts save time but can also lead to mistakes when emotions take over. Slowing down and considering different viewpoints helps create more balanced decisions. Over time, experience teaches people when to trust their instincts and when to pause for deeper thought. Good judgment is not about speed—it's about matching action to the situation.

Sheet Read in Daily Life
A1: # | B1: Set | C1: Passage | D1: Format | E1: Question type | F1: Question | G1: A | H1: B | I1: C | J1: D | K1: Key | L1: Correct answer | M1: Explanation
A2: 101 | B2: 1 | C2: Textbook Collection Reminder | D2: email | E2: detail | F2: What will happen if students return their books after December 18? | G2: Their grades may be affected. | H2: They will lose the right to rent again. | I2: They must pay the full price of the book. | J2: They will receive a fine. | K2: D | L2: =INDEX(G2:J2,MATCH(K2,$G$1:$J$1,0)) | M2: D is correct because the email clearly states, “Late returns will result in a small fine.” That means students who return books after December 18 will have to pay a fee. Option A is incorrect because the message never connects late returns to students' grades. Option B is unsupported since there's no mention of losing rental privileges. Option C is also wrong because students won't be charged the full price of the book, only a fine.
A3: 102 | B3: 1 | C3: Textbook Collection Reminder | D3: email | E3: inference | F3: What can be inferred about the bookstore's policy? | G3: It has not experienced a late return before. | H3: It allows communication before the deadline. | I3: It rents books and does not sell them outright. | J3: It will be closed after December 18th for the holiday season. | K3: B | L3: =INDEX(G3:J3,MATCH(K3,$G$1:$J$1,0)) | M3: B is correct because the message says that students who have lost a book should “email the bookstore for instructions before the deadline,” showing that communication before the due date is part of the policy. Option A is incorrect because nothing in the email suggests this is the first time the bookstore has handled late returns. Option C is not supported. The message only talks about rented books, not sales. Option D is also incorrect since the announcement never mentions the bookstore closing for holidays.
A4: 103 | B4: 2 | C4: Office Parking Update | D4: email | E4: purpose | F4: What is the main purpose of this email? | G4: To request feedback on the new visitor parking policies | H4: To inform employees about a new parking arrangement | I4: To announce the cancellation of parking passes for the lot behind Building B | J4: To remind staff to have their entry passes ready for security staff | K4: B | L4: =INDEX(G4:J4,MATCH(K4,$G$1:$J$1,0)) | M4: B is correct because the email explains that the main lot will be “reserved for visitors only” and that employees should park behind Building B, making the purpose to inform staff of a new parking arrangement. Option A is incorrect because it doesn't ask for feedback, only compliance. Option C is wrong—there's no cancellation of passes. Option D is partly related, as the message mentions security checks, but that's not the central purpose of the email.
A5: 104 | B5: 2 | C5: Office Parking Update | D5: email | E5: inference | F5: What can be inferred about next week's parking procedures? | G5: Employees will be allowed to park anywhere | H5: Visitors will need to park behind Building B | I5: Parking passes will be verified more closely than before | J5: The parking policy will return to normal after one week | K5: C | L5: =INDEX(G5:J5,MATCH(K5,$G$1:$J$1,0)) | M5: C is correct because the email notes that “Security staff will be checking passes at the gate during the first week of this change,” implying closer monitoring than before. Option A is incorrect since employees are told exactly where to park. Option B reverses the facts. Visitors, not employees, will use the main lot. Option D is also incorrect; nothing suggests the policy will last only one week.
A6: 105 | B6: 3 | C6: Staff Training Confirmation | D6: email | E6: purpose | F6: What is the main purpose of this email? | G6: To ask Ms. Forester to refrain from bringing outside food or drinks | H6: To announce a change in room location | I6: To remind Ms. Forester to bring her ID badge | J6: To confirm a registration for training | K6: D | L6: =INDEX(G6:J6,MATCH(K6,$G$1:$J$1,0)) | M6: D is correct because the email opens with, “Your registration for the customer service training on August 10 has been confirmed,” clearly identifying its purpose as a registration confirmation. Option A is incorrect because there's no mention of food restrictions. Option B is wrong because the room location, Conference Room 3, is already final. Option C is partly true since the email does remind Ms. Forester to bring her ID badge, but that's only one detail, not the main message.
A7: 106 | B7: 3 | C7: Staff Training Confirmation | D7: email | E7: negative fact | F7: Which of the following is NOT true according to the email? | G7: Participants need to bring an ID badge. | H7: The training will take place in Conference Room 3. | I7: Lunch will be provided during the session. | J7: Refreshments will be available. | K7: C | L7: =INDEX(G7:J7,MATCH(K7,$G$1:$J$1,0)) | M7: C is correct because the message says, “Refreshments will be provided, but lunch is not included,” so it's false to say lunch will be provided. Option A is true since participants are told to bring an ID badge. Option B is also true because the session is in Conference Room 3. Option D is confirmed in the same sentence about refreshments.
A8: 107 | B8: 4 | C8: Building C Elevator Service | D8: notice | E8: detail | F8: Why will the elevator in Building C be unavailable? | G8: It will undergo a safety inspection. | H8: It will be replaced with a newer model. | I8: It will be inspected and painted. | J8: It will have a light tune-up on the motor. | K8: A | L8: =INDEX(G8:J8,MATCH(K8,$G$1:$J$1,0)) | M8: A is correct because the notice explains that the elevator will be out of service “for a full safety inspection and routine maintenance.” Option B is incorrect since there's no mention of replacement. Option C introduces painting, which isn't mentioned, and option D minimizes the scope. It's more than a “light tune-up.”
A9: 108 | B9: 4 | C9: Building C Elevator Service | D9: notice | E9: detail | F9: What should employees who work on upper floors do on June 12? | G9: Wait until the inspection ends before returning to work | H9: Use Building D to reach their offices | I9: Try the functioning elevator in Building C | J9: Follow the signs up the stairs to their offices | K9: B | L9: =INDEX(G9:J9,MATCH(K9,$G$1:$J$1,0)) | M9: B is correct because the announcement advises staff to “use the stairs or access Building D, which has a functioning elevator.” Option A is incorrect because employees are expected to keep working, not wait for repairs. Option C is wrong because the Building C elevator will not be functioning that day. Option D misinterprets the signs; they're simply for directions, not an instruction to “follow signs up the stairs.”
A10: 109 | B10: 5 | C10: Customer Service Hotline Hours | D10: notice | E10: detail | F10: What change will occur starting October 3? | G10: Representatives will start working full-time. | H10: Sunday service will become available. | I10: Customer support will move online during business hours. | J10: The hotline will stay open one hour later each evening. | K10: D | L10: =INDEX(G10:J10,MATCH(K10,$G$1:$J$1,0)) | M10: D is correct because the notice states, “the schedule has been extended by one hour each evening,” meaning the hotline will stay open one hour later starting October 3. Option A is incorrect because it doesn't mention full-time status. Option B is wrong because Sunday service remains unavailable. Option C is also incorrect since online help is offered outside business hours.
A11: 110 | B11: 5 | C11: Customer Service Hotline Hours | D11: notice | E11: detail | F11: Why are customers encouraged to use the online help form? | G11: It is required for all technical issues. | H11: It provides faster responses than phone support. | I11: It can be accessed when the hotline is closed. | J11: It replaces phone support during business hours. | K11: C | L11: =INDEX(G11:J11,MATCH(K11,$G$1:$J$1,0)) | M11: C is correct because the announcement says customers can use the online form “outside business hours,” meaning it's available when the hotline is closed. Option A is incorrect because customers aren't required to use the form for all issues. Option B is unsupported; there's no claim it's faster. Option D is also wrong since phone support still operates during business hours.
A12: 111 | B12: 6 | C12: Open-House Volunteer Schedule | D12: chat | E12: purpose | F12: What is the main purpose of the messages? | G12: To assign volunteers for a campus event | H12: To choose a location for the open house | I12: To invite students to volunteer for an open house event | J12: To announce a change to the volunteering participants | K12: A | L12: =INDEX(G12:J12,MATCH(K12,$G$1:$J$1,0)) | M12: A is correct because the entire exchange revolves around confirming and assigning volunteers for the campus open-house event. Priya organizes shifts, Jun confirms his group, and Marco volunteers to train others. Option B is incorrect because they already have a location. Option C is wrong because no one is inviting new volunteers. Option D is also incorrect since the team isn't changing participants, just finalizing plans.
A13: 112 | B13: 6 | C13: Open-House Volunteer Schedule | D13: chat | E13: inference | F13: What can be inferred about last semester's event? | G13: The app training took too long | H13: The visitor check-in system did not work smoothly | I13: There were not enough volunteers available | J13: Few visitors came to the event | K13: B | L13: =INDEX(G13:J13,MATCH(K13,$G$1:$J$1,0)) | M13: B is correct because Priya says Marco's demo “should prevent the confusion we had at last semester's event,” implying that the visitor check-in system didn't run smoothly last time. Option A is incorrect; there's no sign the training was too long. Option C is unsupported. Everyone seems to have enough help. Option D is false because the issue was confusion, not low attendance.
... A35: 134 | B35: 13 | C35: Oakridge Community Pool | D35: notice | E35: negative fact | F35: The notice does NOT advise members to | G35: Anticipate a three-day extension being applied to memberships | H35: Direct membership or scheduling questions to the front desk | I35: Continue using the gym and tennis courts during regular hours | J35: Expect complimentary guest passes during the closure period | K35: D | L35: =INDEX(G35:J35,MATCH(K35,$G$1:$J$1,0)) | M35: D is correct because there is no statement suggesting members will receive free guest passes. A, B, and C are all accurate details from the notice. Members are told to expect the three-day extension, contact the front desk for questions, and continue using the gym and tennis courts on their regular schedule.

Sheet Read an Academic Passage
A1: # | B1: Set | C1: Passage | D1: Format | E1: Question type | F1: Question | G1: A | H1: B | I1: C | J1: D | K1: Key | L1: Correct answer | M1: Explanation
A2: 135 | B2: 1 | C2: The Evolution of Money | D2: article | E2: detail | F2: According to the passage, what problem made barter an inefficient system of trade? | G2: Each trader had to want what the other person offered. | H2: Barter required government supervision to be fair. | I2: Farmers could not determine the quality of exchanged goods. | J2: Early societies needed to adopt the same system of beads and shells. | K2: A | L2: =INDEX(G2:J2,MATCH(K2,$G$1:$J$1,0)) | M2: A is correct because the passage states that barter worked only when both traders wanted exactly what the other offered, which made exchanges inefficient. This lack of mutual desire for goods created serious limits to trade. The statement in B about government supervision is not mentioned at all. The idea in C that farmers could not judge quality is unrelated, and D confuses the timeline since shells and beads came later as substitutes for barter.
A3: 136 | B3: 1 | C3: The Evolution of Money | D3: article | E3: detail | F3: What was one effect of the invention of coinage around 600 BCE? | G3: It caused shells and beads to lose their economic importance. | H3: It promoted trade over long distances by creating standardized value. | I3: It diminished the need for paper money in later economies. | J3: It restricted commerce to only places that used stamped metal pieces. | K3: B | L3: =INDEX(G3:J3,MATCH(K3,$G$1:$J$1,0)) | M3: B is correct as the text notes that stamped coins “allowed long-distance trade to flourish” by guaranteeing weight and purity. This innovation created standardized value that promoted broader commerce. A is inaccurate since coins did not instantly replace earlier forms like shells. C is false because paper money emerged much later, and D misinterprets the effect by suggesting coinage restricted trade rather than expanded it.
A4: 137 | B4: 1 | C4: The Evolution of Money | D4: article | E4: vocabulary | F4: The word “durability” in the passage is closest in meaning to | G4: purity | H4: rarity | I4: weight | J4: strength | K4: D | L4: =INDEX(G4:J4,MATCH(K4,$G$1:$J$1,0)) | M4: D is correct because “durability” refers to strength or lasting quality. The author highlights that early materials like metals and shells were chosen for their ability to endure wear over time. The other words do not fit this meaning. Purity relates to content, rarity to scarcity, and weight to heaviness rather than endurance.
A5: 138 | B5: 1 | C5: The Evolution of Money | D5: article | E5: rhetorical purpose | F5: Why does the author mention the “double coincidence of wants”? | G5: To define an early form of currency used in ancient markets | H5: To illustrate why barter created obstacles that money later solved | I5: To explain why some societies still rely on trade without money | J5: To introduce a technical term that describes how bartering led to coin-making | K5: B | L5: =INDEX(G5:J5,MATCH(K5,$G$1:$J$1,0)) | M5: B is correct because the phrase “double coincidence of wants” illustrates why barter created difficulties that money helped resolve. The author introduces it to show the motivation for inventing more flexible exchange systems. A is not correct because it is not describing an early currency. The idea in C that some societies still rely on trade without money goes beyond what the text says. D overstates the point since the phrase explains the problem, not the invention of coins directly.
A6: 139 | B6: 1 | C6: The Evolution of Money | D6: article | E6: insert text | F6: Look at the four squares that indicate where the following sentence could be added to the passage. “This innovation allowed goods to be traded more easily across regions and cultures.” Where would the sentence best fit? | G6: Square A | H6: Square B | I6: Square C | J6: Square D | K6: C | L6: =INDEX(G6:J6,MATCH(K6,$G$1:$J$1,0)) | M6: The sentence fits best at position C. It connects naturally after describing “The invention of coinage around 600 BCE.” A is incorrect because no innovation has been described yet. Option B doesn't work because it describes multiple innovations, “Early societies adopted shells, beads, and metals,” not just one. And option D does not match the flow of the paragraph, making C the best option.
A7: 140 | B7: 2 | C7: The Hidden Life of Soil | D7: article | E7: detail | F7: According to the passage, what enables soil to act as a “living factory”? | G7: The balance of oxygen and water maintained by plant roots | H7: The minerals that form naturally in the soil over time | I7: The constant addition of fertilizers invented by microorganisms | J7: The interaction of countless organisms that release nutrients | K7: D | L7: =INDEX(G7:J7,MATCH(K7,$G$1:$J$1,0)) | M7: D is correct because the author explains that billions of microorganisms interact within soil to release nutrients for plant growth, turning it into a “living factory.” The other choices miss this focus. A mentions oxygen and water, which are not discussed. B talks about minerals forming naturally, but that is not part of the explanation. C is inaccurate since fertilizers are man-made, not produced by microorganisms.
A8: 141 | B8: 2 | C8: The Hidden Life of Soil | D8: article | E8: negative fact | F8: All of the following are described in the passage as outcomes of soil degradation EXCEPT | G8: The loss of microbial diversity | H8: Increased release of carbon into the atmosphere | I8: Greater public recognition of underground ecological change | J8: Rising greenhouse gas concentrations | K8: C | L8: =INDEX(G8:J8,MATCH(K8,$G$1:$J$1,0)) | M8: C is correct because the passage never claims that soil degradation leads to greater public attention. In fact, it says the opposite, calling it a “quiet crisis.” The other three outcomes are all described in the text. The loss of microbial diversity, carbon release into the air, and rising greenhouse gases are presented as clear consequences.
A9: 142 | B9: 2 | C9: The Hidden Life of Soil | D9: article | E9: sentence select | F9: Click on the sentence that explains why soil degradation often goes unnoticed compared to other environmental problems. | G9: As these microorganisms decline, carbon that was once stored underground escapes into the atmosphere, adding to greenhouse gases. | H9: Because these changes occur below the surface, scientists describe soil degradation as a “quiet crisis” that receives far less attention than deforestation or melting ice. | I9: Some regions are now demonstrating how soil recovery can work in practice. | J9: In India, farmers who rotate rice and lentil crops are restoring nitrogen levels naturally. | K9: B | L9: =INDEX(G9:J9,MATCH(K9,$G$1:$J$1,0)) | M9: B is correct. “Because these changes occur below the surface, scientists describe soil degradation as a ‘quiet crisis' that receives far less attention than deforestation or melting ice.” This sentence best explains why soil degradation often goes unnoticed compared with other environmental problems.
A10: 143 | B10: 2 | C10: The Hidden Life of Soil | D10: article | E10: vocabulary | F10: The word “inert” in the passage is closest in meaning to | G10: complex | H10: valuable | I10: motionless | J10: fragile | K10: C | L10: =INDEX(G10:J10,MATCH(K10,$G$1:$J$1,0)) | M10: C is correct since “inert” means still or motionless. The author uses it to emphasize the contrast between soil's lifeless appearance and its hidden activity. A does not work because the author calls soil dynamic, not complex in that sense. B and D are also off base because “inert” has nothing to do with value or fragility.
A11: 144 | B11: 2 | C11: The Hidden Life of Soil | D11: article | E11: rhetorical purpose | F11: Why does the author refer to farming practices in India? | G11: To argue that crop rotation is no longer necessary in modern farming | H11: To contrast traditional techniques with industrial fertilizer use | I11: To show a successful example of restoring soil health | J11: To highlight regions most affected by carbon loss from soil | K11: C | L11: =INDEX(G11:J11,MATCH(K11,$G$1:$J$1,0)) | M11: C is correct because the example from India shows how rotating rice and lentil crops restores soil nitrogen naturally, demonstrating successful soil recovery. The other choices do not match the author's purpose. A is incorrect since the text supports, rather than dismisses, crop rotation. B is partly related but misses the positive outcome being emphasized. D does not fit because India is cited for innovation, not for severe damage.
A12: 145 | B12: 3 | C12: The Double Edge of Facial Recognition | D12: article | E12: main idea | F12: What is the main idea of the passage? | G12: Facial recognition offers both convenience and risks. | H12: Governments should ban facial recognition because it violates civil liberties. | I12: The success of facial recognition depends on its technological accuracy. | J12: The London system has proven that large-scale surveillance is reliable. | K12: A | L12: =INDEX(G12:J12,MATCH(K12,$G$1:$J$1,0)) | M12: A is correct because the passage explores both the advantages and dangers of facial recognition technology. The author notes its convenience and efficiency but also raises concerns about privacy and surveillance. B goes too far by calling for a ban, which the passage never suggests. C captures only one part of the issue by focusing on accuracy, and D misrepresents the author's point since the London system is not described as completely reliable.
A13: 146 | B13: 3 | C13: The Double Edge of Facial Recognition | D13: article | E13: vocabulary | F13: The word “ambitious” in the passage is closest in meaning to | G13: reliable | H13: careful | I13: secret | J13: extensive | K13: D | L13: =INDEX(G13:J13,MATCH(K13,$G$1:$J$1,0)) | M13: D is correct because “ambitious” describes the scale of London's facial recognition network, meaning extensive or far-reaching. Reliable and careful do not fit the context, and secret is opposite in meaning since the program operates publicly on city streets.
... A26: 159 | B26: 5 | C26: The Rise of the Telegraph | D26: article | E26: connect ideas | F26: What is the relationship between paragraphs 2 and 3? | G26: Paragraph 3 provides detailed examples of how Morse's code was transmitted. | H26: Paragraph 3 contrasts the telegraph with newer communication inventions. | I26: Paragraph 3 introduces problems caused by the telegraph's invention. | J26: Paragraph 3 explains the broader impact of the developments described in paragraph 2. | K26: D | L26: =INDEX(G26:J26,MATCH(K26,$G$1:$J$1,0)) | M26: D is correct because the third paragraph expands on the developments described earlier, explaining how the telegraph's invention influenced politics, business, and daily life. The new paragraph shifts from historical detail to overall impact. The other options do not fit since there are no transmission examples, contrasts with newer inventions, or major problems described.

Sheet Passages
A1: Set | B1: Section | C1: Title | D1: Format | E1: Directions | F1: Questions | G1: Full text
A2: dl-1 | B2: Read in Daily Life | C2: Textbook Collection Reminder | D2: email | E2: Read an email. | F2: 101–102 | G2: Subject: Textbook Collection Reminder Dear Students, If you rented textbooks this semester, please return them to the campus bookstore by December 18. Late returns will result in a small fine. Students who have lost a book should email the bookstore for instructions before the deadline. Best, Mimi Chen
A3: dl-2 | B3: Read in Daily Life | C3: Office Parking Update | D3: email | E3: Read an email. | F3: 103–104 | G3: Subject: Office Parking Update Dear Team, Starting Monday, the main parking lot will be reserved for visitors only. Employees should park in the lot behind Building B instead. Please update your parking passes by Friday to avoid any issues next week. Security staff will be checking passes at the gate during the first week of this change. Kind regards, Tom Hardwick
A4: dl-3 | B4: Read in Daily Life | C4: Staff Training Confirmation | D4: email | E4: Read an email. | F4: 105–106 | G4: Subject: Staff Training Confirmation Dear Ms. Forester, Your registration for the customer service training on August 10 has been confirmed. The session will begin at 9:00 a.m. in Conference Room 3. Please bring your ID badge. Refreshments will be provided, but lunch is not included. Sincerely, Ahmed Khan
A5: dl-4 | B5: Read in Daily Life | C5: Building C Elevator Service | D5: notice | E5: Read an announcement. | F5: 107–108 | G5: The elevator in Building C will be out of service all day on Wednesday, June 12, for a full safety inspection and routine maintenance. Employees who work on upper floors should plan accordingly by using the stairs or accessing Building D, which has a functioning elevator. Signs will be posted near the main lobby to guide staff to alternative routes.
A6: dl-5 | B6: Read in Daily Life | C6: Customer Service Hotline Hours | D6: notice | E6: Read an announcement. | F6: 109–110 | G6: The customer service hotline will operate under new hours beginning October 3. Representatives will be available from 9:00 a.m. to 6:00 p.m., Monday through Saturday. Although the schedule has been extended by one hour each evening, Sunday service will remain unavailable. Customers are encouraged to use the online help form outside business hours.
A7: dl-6 | B7: Read in Daily Life | C7: Open-House Volunteer Schedule | D7: chat | E7: Read a text chain. | F7: 111–113 | G7: Priya Singh (2:00 P.M.): Hi everyone, just a reminder that the volunteer schedule for Saturday's campus open-house event needs to be finalized today. Jun Kim (2:04 P.M.): I've already confirmed the morning shift with three students from the debate club. Mimi Chen (2:06 P.M.): Great! I'll handle the afternoon shift sign-ups. Should I assign two people to each information table again? Priya Singh (2:08 P.M.): Yes, please. Also, make sure one volunteer at each table knows how to log visitor check-ins on the tablet. Marco Mercado (2:10 P.M.): I can run a quick demo session tomorrow morning to show everyone how the app works. Priya Singh (2:12 P.M.): Perfect, Marco. That should prevent the confusion we had at last semester's event. Thanks, everyone.
A8: dl-7 | B8: Read in Daily Life | C8: EcoBlend Shipment Delay | D8: chat | E8: Read a text chain. | F8: 114–116 | G8: Olga Antonov (9:00 A.M.): Morning team. The shipment of EcoBlend mugs was delayed due to the storm. We need to update our customers right away. Luis Fernandez (9:03 A.M.): I'll email all wholesale clients explaining the new delivery date. Do we know when the shipment will arrive? Olga Antonov (9:05 A.M.): The supplier expects delivery on Thursday instead of Tuesday. Yasmin Hasan (9:08 A.M.): Should I also post an announcement on our website and social media pages? Olga Antonov (9:10 A.M.): Yes, please do. Keep the message positive—mention the weather issue but emphasize that orders will ship later this week. Ahmed Khan (9:12 A.M.): Got it. I'll adjust the inventory page so customers can't place new mug orders until Thursday. Olga Antonov (9:14 A.M.): Thanks, everyone. Let's avoid the kind of confusion we had during last month's delay.
A9: dl-8 | B9: Read in Daily Life | C9: Conference Slide Deck | D9: chat | E9: Read a text chain. | F9: 117–119 | G9: Michelle Gerber (11:00 A.M.): Hi team, just checking—has everyone uploaded their slides for the environmental conference next week? Hiro Matsumoto (11:03 A.M.): I uploaded mine last night. It focuses on the data from our recycling pilot program. Ela Dogan (11:05 A.M.): I'm still adjusting a few charts, but I'll upload my file before the end of the day. Michelle Gerber (11:07 A.M.): Great, thank you. I'll combine all the slides into one deck so the transitions look consistent. Alex Petrov (11:10 A.M.): Should we include the community outreach results, or would that make the presentation too long? Michelle Gerber (11:13 A.M.): Good question. Let's skip them for now—there's only ten minutes for our session, and we don't want to rush.
A10: dl-9 | B10: Read in Daily Life | C10: Academic Mentorship Program | D10: email | E10: Read an email. | F10: 120–122 | G10: Subject: Invitation to Join the Academic Mentorship Program Dear Students, We are pleased to announce the launch of the university's Academic Mentorship Program for the upcoming semester. The initiative pairs first-year students with experienced upper-class mentors who can offer guidance on study strategies, time management, and adjusting to campus life. If you are interested in becoming a mentor, please complete the short application form on the Student Success Center website by February 14. Training sessions for selected mentors will take place during the last week of February. Participants will receive volunteer-hour certificates and a letter of recognition from the Dean's Office. This program has helped hundreds of students feel more connected and confident in their academic journey. We encourage you to get involved and make a positive difference in someone else's experience. Warm regards, Aisha Hinds
A11: dl-10 | B11: Read in Daily Life | C11: Temporary Relocation of HR | D11: email | E11: Read an email. | F11: 123–125 | G11: Subject: Temporary Relocation of HR Department The Human Resources Department will be temporarily relocated to Suite 402 while renovations are completed on the main office. The relocation will take effect on June 12 and is expected to last three weeks. During this period, employees should visit Suite 402 for payroll questions, benefits assistance, or onboarding meetings. All appointments already scheduled in the main office will continue as planned. Visitors may notice directional signs near the elevator and at the entrance to each floor. The HR team will maintain normal business hours and can still be reached by phone or email for general inquiries. These improvements include updated workstations and a more private meeting area for confidential consultations. Thank you for your patience and cooperation as we create a more efficient and comfortable workspace for everyone. — The Facilities Department
A12: dl-11 | B12: Read in Daily Life | C12: Water Service Interruption | D12: email | E12: Read an email. | F12: 126–128 | G12: Subject: Important Update – Water Service Interruption Dear Residents, Please be advised that routine maintenance on the neighborhood's main water line is scheduled for Tuesday, September 17, from 9:00 A.M. to 3:00 P.M. During this time, water service will be temporarily unavailable in all residential units. Residents are encouraged to store an adequate supply of water for cooking, cleaning, and drinking before the interruption begins. The maintenance crew will make every effort to complete the work on schedule, but delays may occur if unexpected repairs are required. Once service resumes, we recommend running the tap for several minutes to clear any air or discoloration from the pipes. We appreciate your understanding and cooperation as we complete this necessary maintenance to ensure the long-term reliability of the system.
... A19: ap-5 | B19: Read an Academic Passage | C19: The Rise of the Telegraph | D19: article | E19: Read an academic passage. Answer the questions that follow. | F19: 155–159 | G19: The Rise of the Telegraph Before the nineteenth century, communication could travel only as fast as a messenger on horseback or a ship at sea. News, orders, and personal letters often took weeks or months to reach their destinations. That changed dramatically with the invention of the telegraph. Using electric signals sent through wires, people could transmit messages across vast distances in seconds, transforming both business and daily life. The first major network was developed in the 1840s by Samuel Morse in the United States. His system converted words into patterns of short and long electrical pulses, known as Morse code. Telegraph offices soon lined railroad stations, allowing traders to track prices and newspapers to report events almost as they happened. During the American Civil War, generals used the telegraph to coordinate troop movements, demonstrating how information could become as decisive as weaponry. Similar systems spread across Europe and later under the oceans, connecting continents through submarine cables. The telegraph compressed the world. It reshaped politics, commerce, and journalism by introducing the idea of instant communication. Though later replaced by telephones and the internet, the telegraph laid the first electronic foundation for the global networks that now link nearly every part of human society.
